basic-config-loader/__init__.py
basic_config_loader/__init__.py
configLoader/__init__.py
basic_config_loader-0.2.0.dist-info/LICENSE
basic_config_loader-0.2.0.dist-info/METADATA
basic_config_loader-0.2.0.dist-info/WHEEL
basic_config_loader-0.2.0.dist-info/top_level.txt
basic_config_loader-0.2.0.dist-info/RECORD
