Metadata-Version: 2.1
Name: basic-config-loader
Version: 0.2.0
Summary: A basic configuration loader intended for my own scripts, but might be useful for other people.
Home-page: https://gitlab.com/0100001001000010/config-loader
Author: Bruce Blore
Author-email: bruceblore@protonmail.com
License: UNKNOWN
Platform: UNKNOWN
Classifier: Programming Language :: Python :: 3
Classifier: License :: OSI Approved :: MIT License
Classifier: Operating System :: OS Independent
